.gitignore
README.rst
setup.py
Nikwus.egg-info/PKG-INFO
Nikwus.egg-info/SOURCES.txt
Nikwus.egg-info/dependency_links.txt
Nikwus.egg-info/requires.txt
Nikwus.egg-info/top_level.txt
nikwus/__init__.py
tests/test_spriting.py
tests/autosize/accept.png
tests/autosize/arrow.png
tests/autosize/folder.png
tests/autosize/test-expected.css
tests/autosize/test.css
tests/autosize/world.png
tests/media-queries/test-expected.css
tests/media-queries/test.css
tests/minimal/accept.png
tests/minimal/test-expected.css
tests/minimal/test.css
tests/minimal/world.png
tests/multi/accept.png
tests/multi/folder.png
tests/multi/test-expected.css
tests/multi/test.css
tests/multi/world.png
tests/no-autosize/accept.png
tests/no-autosize/arrow.png
tests/no-autosize/folder.png
tests/no-autosize/test-expected.css
tests/no-autosize/test.css
tests/no-autosize/world.png
tests/no-container/accept.png
tests/no-container/test-expected.css
tests/no-container/test.css
tests/no-container/world.png
tests/no-sprite/accept.png
tests/no-sprite/folder.png
tests/no-sprite/loader.gif
tests/no-sprite/test-expected.css
tests/no-sprite/test.css
tests/retina/add-2x.png
tests/retina/add.png
tests/retina/arrow-back-2x.png
tests/retina/arrow-back.png
tests/retina/default-2x.png
tests/retina/test-expected.css
tests/retina/test.css
tests/split/accept.png
tests/split/arrow.png
tests/split/folder.png
tests/split/test-expected.css
tests/split/test.css
tests/split/world.png
tests/split-no-container/accept.png
tests/split-no-container/arrow.png
tests/split-no-container/folder.png
tests/split-no-container/test-expected.css
tests/split-no-container/test.css
tests/split-no-container/world.png
tests/subdir/css/test-expected.css
tests/subdir/css/test.css
tests/subdir/img/accept.png
tests/subdir/img/world.png