Metadata-Version: 1.1
Name: Nikwus
Version: 0.5.3
Summary: Automatically sprite images in CSS files
Home-page: UNKNOWN
Author: Patrice Neff <mail@patrice.ch>
Author-email: UNKNOWN
License: BSD
Platform: UNKNOWN
Classifier: Development Status :: 4 - Beta
Classifier: Intended Audience :: Developers
Classifier: License :: OSI Approved :: BSD License
Classifier: Topic :: Internet :: WWW/HTTP :: Site Management
Classifier: Topic :: Multimedia :: Graphics :: Graphics Conversion
